<?xml version="1.0" encoding="utf-8"?>
<!--Exported: TS-21_Birdeater_Wanted_List.xml Date: 11/5/15 4:06 PM-->
<INVENTORY>
<ITEM>
<ITEMTYPE>P</ITEMTYPE>
<ITEMID>4274</ITEMID>
<COLOR>86</COLOR>
<MINQTY>38</MINQTY>
<NOTIFY>N</NOTIFY>
<WANTEDSHOW>N</WANTEDSHOW>
<CONDITION></CONDITION>
<WANTEDLISTID>REPLACEME</WANTEDLISTID>
</ITEM>
<ITEM>
<ITEMTYPE>P</ITEMTYPE>
<ITEMID>99780</ITEMID>
<COLOR>85</COLOR>
<MINQTY>12</MINQTY>
<NOTIFY>N</NOTIFY>
<WANTEDSHOW>N</WANTEDSHOW>
<CONDITION></CONDITION>
<WANTEDLISTID>REPLACEME</WANTEDLISTID>
</ITEM>
<ITEM>
<ITEMTYPE>P</ITEMTYPE>
<ITEMID>3023</ITEMID>
<COLOR>85</COLOR>
<MINQTY>92</MINQTY>
<NOTIFY>N</NOTIFY>
<WANTEDSHOW>N</WANTEDSHOW>
<CONDITION></CONDITION>
<WANTEDLISTID>REPLACEME</WANTEDLISTID>
</ITEM>
<ITEM>
<ITEMTYPE>P</ITEMTYPE>
<ITEMID>3069b</ITEMID>
<COLOR>69</COLOR>
<MINQTY>39</MINQTY>
<NOTIFY>N</NOTIFY>
<WANTEDSHOW>N</WANTEDSHOW>
<CONDITION></CONDITION>
<WANTEDLISTID>REPLACEME</WANTEDLISTID>
</ITEM>
<ITEM>
<ITEMTYPE>P</ITEMTYPE>
<ITEMID>3022</ITEMID>
<COLOR>85</COLOR>
<MINQTY>28</MINQTY>
<NOTIFY>N</NOTIFY>
<WANTEDSHOW>N</WANTEDSHOW>
<CONDITION></CONDITION>
<WANTEDLISTID>REPLACEME</WANTEDLISTID>
</ITEM>
<ITEM>
<ITEMTYPE>P</ITEMTYPE>
<ITEMID>3069b</ITEMID>
<COLOR>85</COLOR>
<MINQTY>27</MINQTY>
<NOTIFY>N</NOTIFY>
<WANTEDSHOW>N</WANTEDSHOW>
<CONDITION></CONDITION>
<WANTEDLISTID>REPLACEME</WANTEDLISTID>
</ITEM>
<ITEM>
<ITEMTYPE>P</ITEMTYPE>
<ITEMID>4150</ITEMID>
<COLOR>69</COLOR>
<MINQTY>8</MINQTY>
<NOTIFY>N</NOTIFY>
<WANTEDSHOW>N</WANTEDSHOW>
<CONDITION></CONDITION>
<WANTEDLISTID>REPLACEME</WANTEDLISTID>
</ITEM>
<ITEM>
<ITEMTYPE>P</ITEMTYPE>
<ITEMID>3937</ITEMID>
<COLOR>85</COLOR>
<MINQTY>4</MINQTY>
<NOTIFY>N</NOTIFY>
<WANTEDSHOW>N</WANTEDSHOW>
<CONDITION></CONDITION>
<WANTEDLISTID>REPLACEME</WANTEDLISTID>
</ITEM>
<ITEM>
<ITEMTYPE>P</ITEMTYPE>
<ITEMID>3938</ITEMID>
<COLOR>86</COLOR>
<MINQTY>4</MINQTY>
<NOTIFY>N</NOTIFY>
<WANTEDSHOW>N</WANTEDSHOW>
<CONDITION></CONDITION>
<WANTEDLISTID>REPLACEME</WANTEDLISTID>
</ITEM>
<ITEM>
<ITEMTYPE>P</ITEMTYPE>
<ITEMID>3062b</ITEMID>
<COLOR>85</COLOR>
<MINQTY>30</MINQTY>
<NOTIFY>N</NOTIFY>
<WANTEDSHOW>N</WANTEDSHOW>
<CONDITION></CONDITION>
<WANTEDLISTID>REPLACEME</WANTEDLISTID>
</ITEM>
<ITEM>
<ITEMTYPE>P</ITEMTYPE>
<ITEMID>3004</ITEMID>
<COLOR>85</COLOR>
<MINQTY>30</MINQTY>
<NOTIFY>N</NOTIFY>
<WANTEDSHOW>N</WANTEDSHOW>
<CONDITION></CONDITION>
<WANTEDLISTID>REPLACEME</WANTEDLISTID>
</ITEM>
<ITEM>
<ITEMTYPE>P</ITEMTYPE>
<ITEMID>3022</ITEMID>
<COLOR>1</COLOR>
<MINQTY>6</MINQTY>
<NOTIFY>N</NOTIFY>
<WANTEDSHOW>N</WANTEDSHOW>
<CONDITION></CONDITION>
<WANTEDLISTID>REPLACEME</WANTEDLISTID>
</ITEM>
<ITEM>
<ITEMTYPE>P</ITEMTYPE>
<ITEMID>4085c</ITEMID>
<COLOR>85</COLOR>
<MINQTY>13</MINQTY>
<NOTIFY>N</NOTIFY>
<WANTEDSHOW>N</WANTEDSHOW>
<CONDITION></CONDITION>
<WANTEDLISTID>REPLACEME</WANTEDLISTID>
</ITEM>
<ITEM>
<ITEMTYPE>P</ITEMTYPE>
<ITEMID>3678b</ITEMID>
<COLOR>85</COLOR>
<MINQTY>4</MINQTY>
<NOTIFY>N</NOTIFY>
<WANTEDSHOW>N</WANTEDSHOW>
<CONDITION></CONDITION>
<WANTEDLISTID>REPLACEME</WANTEDLISTID>
</ITEM>
<ITEM>
<ITEMTYPE>P</ITEMTYPE>
<ITEMID>85984</ITEMID>
<COLOR>85</COLOR>
<MINQTY>10</MINQTY>
<NOTIFY>N</NOTIFY>
<WANTEDSHOW>N</WANTEDSHOW>
<CONDITION></CONDITION>
<WANTEDLISTID>REPLACEME</WANTEDLISTID>
</ITEM>
<ITEM>
<ITEMTYPE>P</ITEMTYPE>
<ITEMID>30374</ITEMID>
<COLOR>86</COLOR>
<MINQTY>12</MINQTY>
<NOTIFY>N</NOTIFY>
<WANTEDSHOW>N</WANTEDSHOW>
<CONDITION></CONDITION>
<WANTEDLISTID>REPLACEME</WANTEDLISTID>
</ITEM>
<ITEM>
<ITEMTYPE>P</ITEMTYPE>
<ITEMID>41677</ITEMID>
<COLOR>85</COLOR>
<MINQTY>4</MINQTY>
<NOTIFY>N</NOTIFY>
<WANTEDSHOW>N</WANTEDSHOW>
<CONDITION></CONDITION>
<WANTEDLISTID>REPLACEME</WANTEDLISTID>
</ITEM>
<ITEM>
<ITEMTYPE>P</ITEMTYPE>
<ITEMID>45590</ITEMID>
<COLOR>11</COLOR>
<MINQTY>4</MINQTY>
<NOTIFY>N</NOTIFY>
<WANTEDSHOW>N</WANTEDSHOW>
<CONDITION></CONDITION>
<WANTEDLISTID>REPLACEME</WANTEDLISTID>
</ITEM>
<ITEM>
<ITEMTYPE>P</ITEMTYPE>
<ITEMID>3070b</ITEMID>
<COLOR>88</COLOR>
<MINQTY>6</MINQTY>
<NOTIFY>N</NOTIFY>
<WANTEDSHOW>N</WANTEDSHOW>
<CONDITION></CONDITION>
<WANTEDLISTID>REPLACEME</WANTEDLISTID>
</ITEM>
<ITEM>
<ITEMTYPE>P</ITEMTYPE>
<ITEMID>4460b</ITEMID>
<COLOR>69</COLOR>
<MINQTY>6</MINQTY>
<NOTIFY>N</NOTIFY>
<WANTEDSHOW>N</WANTEDSHOW>
<CONDITION></CONDITION>
<WANTEDLISTID>REPLACEME</WANTEDLISTID>
</ITEM>
<ITEM>
<ITEMTYPE>P</ITEMTYPE>
<ITEMID>3023</ITEMID>
<COLOR>1</COLOR>
<MINQTY>6</MINQTY>
<NOTIFY>N</NOTIFY>
<WANTEDSHOW>N</WANTEDSHOW>
<CONDITION></CONDITION>
<WANTEDLISTID>REPLACEME</WANTEDLISTID>
</ITEM>
<ITEM>
<ITEMTYPE>P</ITEMTYPE>
<ITEMID>3004</ITEMID>
<COLOR>69</COLOR>
<MINQTY>54</MINQTY>
<NOTIFY>N</NOTIFY>
<WANTEDSHOW>N</WANTEDSHOW>
<CONDITION></CONDITION>
<WANTEDLISTID>REPLACEME</WANTEDLISTID>
</ITEM>
<ITEM>
<ITEMTYPE>P</ITEMTYPE>
<ITEMID>4150</ITEMID>
<COLOR>1</COLOR>
<MINQTY>2</MINQTY>
<NOTIFY>N</NOTIFY>
<WANTEDSHOW>N</WANTEDSHOW>
<CONDITION></CONDITION>
<WANTEDLISTID>REPLACEME</WANTEDLISTID>
</ITEM>
<ITEM>
<ITEMTYPE>P</ITEMTYPE>
<ITEMID>3941</ITEMID>
<COLOR>1</COLOR>
<MINQTY>8</MINQTY>
<NOTIFY>N</NOTIFY>
<WANTEDSHOW>N</WANTEDSHOW>
<CONDITION></CONDITION>
<WANTEDLISTID>REPLACEME</WANTEDLISTID>
</ITEM>
<ITEM>
<ITEMTYPE>P</ITEMTYPE>
<ITEMID>30414</ITEMID>
<COLOR>85</COLOR>
<MINQTY>15</MINQTY>
<NOTIFY>N</NOTIFY>
<WANTEDSHOW>N</WANTEDSHOW>
<CONDITION></CONDITION>
<WANTEDLISTID>REPLACEME</WANTEDLISTID>
</ITEM>
<ITEM>
<ITEMTYPE>P</ITEMTYPE>
<ITEMID>3020</ITEMID>
<COLOR>85</COLOR>
<MINQTY>7</MINQTY>
<NOTIFY>N</NOTIFY>
<WANTEDSHOW>N</WANTEDSHOW>
<CONDITION></CONDITION>
<WANTEDLISTID>REPLACEME</WANTEDLISTID>
</ITEM>
<ITEM>
<ITEMTYPE>P</ITEMTYPE>
<ITEMID>11211</ITEMID>
<COLOR>86</COLOR>
<MINQTY>9</MINQTY>
<NOTIFY>N</NOTIFY>
<WANTEDSHOW>N</WANTEDSHOW>
<CONDITION></CONDITION>
<WANTEDLISTID>REPLACEME</WANTEDLISTID>
</ITEM>
<ITEM>
<ITEMTYPE>P</ITEMTYPE>
<ITEMID>3024</ITEMID>
<COLOR>85</COLOR>
<MINQTY>18</MINQTY>
<NOTIFY>N</NOTIFY>
<WANTEDSHOW>N</WANTEDSHOW>
<CONDITION></CONDITION>
<WANTEDLISTID>REPLACEME</WANTEDLISTID>
</ITEM>
<ITEM>
<ITEMTYPE>P</ITEMTYPE>
<ITEMID>3010</ITEMID>
<COLOR>69</COLOR>
<MINQTY>10</MINQTY>
<NOTIFY>N</NOTIFY>
<WANTEDSHOW>N</WANTEDSHOW>
<CONDITION></CONDITION>
<WANTEDLISTID>REPLACEME</WANTEDLISTID>
</ITEM>
<ITEM>
<ITEMTYPE>P</ITEMTYPE>
<ITEMID>11212</ITEMID>
<COLOR>85</COLOR>
<MINQTY>2</MINQTY>
<NOTIFY>N</NOTIFY>
<WANTEDSHOW>N</WANTEDSHOW>
<CONDITION></CONDITION>
<WANTEDLISTID>REPLACEME</WANTEDLISTID>
</ITEM>
<ITEM>
<ITEMTYPE>P</ITEMTYPE>
<ITEMID>3021</ITEMID>
<COLOR>85</COLOR>
<MINQTY>19</MINQTY>
<NOTIFY>N</NOTIFY>
<WANTEDSHOW>N</WANTEDSHOW>
<CONDITION></CONDITION>
<WANTEDLISTID>REPLACEME</WANTEDLISTID>
</ITEM>
<ITEM>
<ITEMTYPE>P</ITEMTYPE>
<ITEMID>2420</ITEMID>
<COLOR>85</COLOR>
<MINQTY>8</MINQTY>
<NOTIFY>N</NOTIFY>
<WANTEDSHOW>N</WANTEDSHOW>
<CONDITION></CONDITION>
<WANTEDLISTID>REPLACEME</WANTEDLISTID>
</ITEM>
<ITEM>
<ITEMTYPE>P</ITEMTYPE>
<ITEMID>41769</ITEMID>
<COLOR>69</COLOR>
<MINQTY>2</MINQTY>
<NOTIFY>N</NOTIFY>
<WANTEDSHOW>N</WANTEDSHOW>
<CONDITION></CONDITION>
<WANTEDLISTID>REPLACEME</WANTEDLISTID>
</ITEM>
<ITEM>
<ITEMTYPE>P</ITEMTYPE>
<ITEMID>47753</ITEMID>
<COLOR>69</COLOR>
<MINQTY>2</MINQTY>
<NOTIFY>N</NOTIFY>
<WANTEDSHOW>N</WANTEDSHOW>
<CONDITION></CONDITION>
<WANTEDLISTID>REPLACEME</WANTEDLISTID>
</ITEM>
<ITEM>
<ITEMTYPE>P</ITEMTYPE>
<ITEMID>41770</ITEMID>
<COLOR>69</COLOR>
<MINQTY>2</MINQTY>
<NOTIFY>N</NOTIFY>
<WANTEDSHOW>N</WANTEDSHOW>
<CONDITION></CONDITION>
<WANTEDLISTID>REPLACEME</WANTEDLISTID>
</ITEM>
<ITEM>
<ITEMTYPE>P</ITEMTYPE>
<ITEMID>6091</ITEMID>
<COLOR>85</COLOR>
<MINQTY>16</MINQTY>
<NOTIFY>N</NOTIFY>
<WANTEDSHOW>N</WANTEDSHOW>
<CONDITION></CONDITION>
<WANTEDLISTID>REPLACEME</WANTEDLISTID>
</ITEM>
<ITEM>
<ITEMTYPE>P</ITEMTYPE>
<ITEMID>2412b</ITEMID>
<COLOR>85</COLOR>
<MINQTY>15</MINQTY>
<NOTIFY>N</NOTIFY>
<WANTEDSHOW>N</WANTEDSHOW>
<CONDITION></CONDITION>
<WANTEDLISTID>REPLACEME</WANTEDLISTID>
</ITEM>
<ITEM>
<ITEMTYPE>P</ITEMTYPE>
<ITEMID>3068b</ITEMID>
<COLOR>85</COLOR>
<MINQTY>3</MINQTY>
<NOTIFY>N</NOTIFY>
<WANTEDSHOW>N</WANTEDSHOW>
<CONDITION></CONDITION>
<WANTEDLISTID>REPLACEME</WANTEDLISTID>
</ITEM>
<ITEM>
<ITEMTYPE>P</ITEMTYPE>
<ITEMID>3010</ITEMID>
<COLOR>85</COLOR>
<MINQTY>3</MINQTY>
<NOTIFY>N</NOTIFY>
<WANTEDSHOW>N</WANTEDSHOW>
<CONDITION></CONDITION>
<WANTEDLISTID>REPLACEME</WANTEDLISTID>
</ITEM>
<ITEM>
<ITEMTYPE>P</ITEMTYPE>
<ITEMID>2431</ITEMID>
<COLOR>1</COLOR>
<MINQTY>2</MINQTY>
<NOTIFY>N</NOTIFY>
<WANTEDSHOW>N</WANTEDSHOW>
<CONDITION></CONDITION>
<WANTEDLISTID>REPLACEME</WANTEDLISTID>
</ITEM>
<ITEM>
<ITEMTYPE>P</ITEMTYPE>
<ITEMID>3623</ITEMID>
<COLOR>85</COLOR>
<MINQTY>3</MINQTY>
<NOTIFY>N</NOTIFY>
<WANTEDSHOW>N</WANTEDSHOW>
<CONDITION></CONDITION>
<WANTEDLISTID>REPLACEME</WANTEDLISTID>
</ITEM>
<ITEM>
<ITEMTYPE>P</ITEMTYPE>
<ITEMID>95188</ITEMID>
<COLOR>69</COLOR>
<MINQTY>4</MINQTY>
<NOTIFY>N</NOTIFY>
<WANTEDSHOW>N</WANTEDSHOW>
<CONDITION></CONDITION>
<WANTEDLISTID>REPLACEME</WANTEDLISTID>
</ITEM>
<ITEM>
<ITEMTYPE>P</ITEMTYPE>
<ITEMID>4286</ITEMID>
<COLOR>1</COLOR>
<MINQTY>4</MINQTY>
<NOTIFY>N</NOTIFY>
<WANTEDSHOW>N</WANTEDSHOW>
<CONDITION></CONDITION>
<WANTEDLISTID>REPLACEME</WANTEDLISTID>
</ITEM>
<ITEM>
<ITEMTYPE>P</ITEMTYPE>
<ITEMID>32028</ITEMID>
<COLOR>69</COLOR>
<MINQTY>12</MINQTY>
<NOTIFY>N</NOTIFY>
<WANTEDSHOW>N</WANTEDSHOW>
<CONDITION></CONDITION>
<WANTEDLISTID>REPLACEME</WANTEDLISTID>
</ITEM>
<ITEM>
<ITEMTYPE>P</ITEMTYPE>
<ITEMID>87079</ITEMID>
<COLOR>85</COLOR>
<MINQTY>2</MINQTY>
<NOTIFY>N</NOTIFY>
<WANTEDSHOW>N</WANTEDSHOW>
<CONDITION></CONDITION>
<WANTEDLISTID>REPLACEME</WANTEDLISTID>
</ITEM>
<ITEM>
<ITEMTYPE>P</ITEMTYPE>
<ITEMID>60478</ITEMID>
<COLOR>85</COLOR>
<MINQTY>16</MINQTY>
<NOTIFY>N</NOTIFY>
<WANTEDSHOW>N</WANTEDSHOW>
<CONDITION></CONDITION>
<WANTEDLISTID>REPLACEME</WANTEDLISTID>
</ITEM>
<ITEM>
<ITEMTYPE>P</ITEMTYPE>
<ITEMID>87087</ITEMID>
<COLOR>85</COLOR>
<MINQTY>34</MINQTY>
<NOTIFY>N</NOTIFY>
<WANTEDSHOW>N</WANTEDSHOW>
<CONDITION></CONDITION>
<WANTEDLISTID>REPLACEME</WANTEDLISTID>
</ITEM>
<ITEM>
<ITEMTYPE>P</ITEMTYPE>
<ITEMID>48729b</ITEMID>
<COLOR>85</COLOR>
<MINQTY>6</MINQTY>
<NOTIFY>N</NOTIFY>
<WANTEDSHOW>N</WANTEDSHOW>
<CONDITION></CONDITION>
<WANTEDLISTID>REPLACEME</WANTEDLISTID>
</ITEM>
<ITEM>
<ITEMTYPE>P</ITEMTYPE>
<ITEMID>3023</ITEMID>
<COLOR>69</COLOR>
<MINQTY>11</MINQTY>
<NOTIFY>N</NOTIFY>
<WANTEDSHOW>N</WANTEDSHOW>
<CONDITION></CONDITION>
<WANTEDLISTID>REPLACEME</WANTEDLISTID>
</ITEM>
<ITEM>
<ITEMTYPE>P</ITEMTYPE>
<ITEMID>3005</ITEMID>
<COLOR>85</COLOR>
<MINQTY>19</MINQTY>
<NOTIFY>N</NOTIFY>
<WANTEDSHOW>N</WANTEDSHOW>
<CONDITION></CONDITION>
<WANTEDLISTID>REPLACEME</WANTEDLISTID>
</ITEM>
<ITEM>
<ITEMTYPE>P</ITEMTYPE>
<ITEMID>3009</ITEMID>
<COLOR>85</COLOR>
<MINQTY>1</MINQTY>
<NOTIFY>N</NOTIFY>
<WANTEDSHOW>N</WANTEDSHOW>
<CONDITION></CONDITION>
<WANTEDLISTID>REPLACEME</WANTEDLISTID>
</ITEM>
<ITEM>
<ITEMTYPE>P</ITEMTYPE>
<ITEMID>3069b</ITEMID>
<COLOR>12</COLOR>
<MINQTY>1</MINQTY>
<NOTIFY>N</NOTIFY>
<WANTEDSHOW>N</WANTEDSHOW>
<CONDITION></CONDITION>
<WANTEDLISTID>REPLACEME</WANTEDLISTID>
</ITEM>
<ITEM>
<ITEMTYPE>P</ITEMTYPE>
<ITEMID>3460</ITEMID>
<COLOR>85</COLOR>
<MINQTY>1</MINQTY>
<NOTIFY>N</NOTIFY>
<WANTEDSHOW>N</WANTEDSHOW>
<CONDITION></CONDITION>
<WANTEDLISTID>REPLACEME</WANTEDLISTID>
</ITEM>
<ITEM>
<ITEMTYPE>P</ITEMTYPE>
<ITEMID>3008</ITEMID>
<COLOR>85</COLOR>
<MINQTY>1</MINQTY>
<NOTIFY>N</NOTIFY>
<WANTEDSHOW>N</WANTEDSHOW>
<CONDITION></CONDITION>
<WANTEDLISTID>REPLACEME</WANTEDLISTID>
</ITEM>
<ITEM>
<ITEMTYPE>P</ITEMTYPE>
<ITEMID>3684</ITEMID>
<COLOR>69</COLOR>
<MINQTY>8</MINQTY>
<NOTIFY>N</NOTIFY>
<WANTEDSHOW>N</WANTEDSHOW>
<CONDITION></CONDITION>
<WANTEDLISTID>REPLACEME</WANTEDLISTID>
</ITEM>
<ITEM>
<ITEMTYPE>P</ITEMTYPE>
<ITEMID>3020</ITEMID>
<COLOR>1</COLOR>
<MINQTY>2</MINQTY>
<NOTIFY>N</NOTIFY>
<WANTEDSHOW>N</WANTEDSHOW>
<CONDITION></CONDITION>
<WANTEDLISTID>REPLACEME</WANTEDLISTID>
</ITEM>
<ITEM>
<ITEMTYPE>P</ITEMTYPE>
<ITEMID>3001</ITEMID>
<COLOR>85</COLOR>
<MINQTY>7</MINQTY>
<NOTIFY>N</NOTIFY>
<WANTEDSHOW>N</WANTEDSHOW>
<CONDITION></CONDITION>
<WANTEDLISTID>REPLACEME</WANTEDLISTID>
</ITEM>
<ITEM>
<ITEMTYPE>P</ITEMTYPE>
<ITEMID>3040</ITEMID>
<COLOR>69</COLOR>
<MINQTY>16</MINQTY>
<NOTIFY>N</NOTIFY>
<WANTEDSHOW>N</WANTEDSHOW>
<CONDITION></CONDITION>
<WANTEDLISTID>REPLACEME</WANTEDLISTID>
</ITEM>
<ITEM>
<ITEMTYPE>P</ITEMTYPE>
<ITEMID>4073</ITEMID>
<COLOR>85</COLOR>
<MINQTY>51</MINQTY>
<NOTIFY>N</NOTIFY>
<WANTEDSHOW>N</WANTEDSHOW>
<CONDITION></CONDITION>
<WANTEDLISTID>REPLACEME</WANTEDLISTID>
</ITEM>
<ITEM>
<ITEMTYPE>P</ITEMTYPE>
<ITEMID>3040</ITEMID>
<COLOR>85</COLOR>
<MINQTY>4</MINQTY>
<NOTIFY>N</NOTIFY>
<WANTEDSHOW>N</WANTEDSHOW>
<CONDITION></CONDITION>
<WANTEDLISTID>REPLACEME</WANTEDLISTID>
</ITEM>
<ITEM>
<ITEMTYPE>P</ITEMTYPE>
<ITEMID>3003</ITEMID>
<COLOR>85</COLOR>
<MINQTY>11</MINQTY>
<NOTIFY>N</NOTIFY>
<WANTEDSHOW>N</WANTEDSHOW>
<CONDITION></CONDITION>
<WANTEDLISTID>REPLACEME</WANTEDLISTID>
</ITEM>
<ITEM>
<ITEMTYPE>P</ITEMTYPE>
<ITEMID>3701</ITEMID>
<COLOR>85</COLOR>
<MINQTY>4</MINQTY>
<NOTIFY>N</NOTIFY>
<WANTEDSHOW>N</WANTEDSHOW>
<CONDITION></CONDITION>
<WANTEDLISTID>REPLACEME</WANTEDLISTID>
</ITEM>
<ITEM>
<ITEMTYPE>P</ITEMTYPE>
<ITEMID>3710</ITEMID>
<COLOR>85</COLOR>
<MINQTY>9</MINQTY>
<NOTIFY>N</NOTIFY>
<WANTEDSHOW>N</WANTEDSHOW>
<CONDITION></CONDITION>
<WANTEDLISTID>REPLACEME</WANTEDLISTID>
</ITEM>
<ITEM>
<ITEMTYPE>P</ITEMTYPE>
<ITEMID>3034</ITEMID>
<COLOR>85</COLOR>
<MINQTY>2</MINQTY>
<NOTIFY>N</NOTIFY>
<WANTEDSHOW>N</WANTEDSHOW>
<CONDITION></CONDITION>
<WANTEDLISTID>REPLACEME</WANTEDLISTID>
</ITEM>
<ITEM>
<ITEMTYPE>P</ITEMTYPE>
<ITEMID>2432</ITEMID>
<COLOR>85</COLOR>
<MINQTY>4</MINQTY>
<NOTIFY>N</NOTIFY>
<WANTEDSHOW>N</WANTEDSHOW>
<CONDITION></CONDITION>
<WANTEDLISTID>REPLACEME</WANTEDLISTID>
</ITEM>
<ITEM>
<ITEMTYPE>P</ITEMTYPE>
<ITEMID>4070</ITEMID>
<COLOR>85</COLOR>
<MINQTY>34</MINQTY>
<NOTIFY>N</NOTIFY>
<WANTEDSHOW>N</WANTEDSHOW>
<CONDITION></CONDITION>
<WANTEDLISTID>REPLACEME</WANTEDLISTID>
</ITEM>
<ITEM>
<ITEMTYPE>P</ITEMTYPE>
<ITEMID>2555</ITEMID>
<COLOR>85</COLOR>
<MINQTY>10</MINQTY>
<NOTIFY>N</NOTIFY>
<WANTEDSHOW>N</WANTEDSHOW>
<CONDITION></CONDITION>
<WANTEDLISTID>REPLACEME</WANTEDLISTID>
</ITEM>
<ITEM>
<ITEMTYPE>P</ITEMTYPE>
<ITEMID>3678b</ITEMID>
<COLOR>69</COLOR>
<MINQTY>4</MINQTY>
<NOTIFY>N</NOTIFY>
<WANTEDSHOW>N</WANTEDSHOW>
<CONDITION></CONDITION>
<WANTEDLISTID>REPLACEME</WANTEDLISTID>
</ITEM>
<ITEM>
<ITEMTYPE>P</ITEMTYPE>
<ITEMID>2584</ITEMID>
<COLOR>11</COLOR>
<MINQTY>1</MINQTY>
<NOTIFY>N</NOTIFY>
<WANTEDSHOW>N</WANTEDSHOW>
<CONDITION></CONDITION>
<WANTEDLISTID>REPLACEME</WANTEDLISTID>
</ITEM>
<ITEM>
<ITEMTYPE>P</ITEMTYPE>
<ITEMID>90258</ITEMID>
<COLOR>85</COLOR>
<MINQTY>5</MINQTY>
<NOTIFY>N</NOTIFY>
<WANTEDSHOW>N</WANTEDSHOW>
<CONDITION></CONDITION>
<WANTEDLISTID>REPLACEME</WANTEDLISTID>
</ITEM>
<ITEM>
<ITEMTYPE>P</ITEMTYPE>
<ITEMID>3710</ITEMID>
<COLOR>1</COLOR>
<MINQTY>2</MINQTY>
<NOTIFY>N</NOTIFY>
<WANTEDSHOW>N</WANTEDSHOW>
<CONDITION></CONDITION>
<WANTEDLISTID>REPLACEME</WANTEDLISTID>
</ITEM>
<ITEM>
<ITEMTYPE>P</ITEMTYPE>
<ITEMID>48169</ITEMID>
<COLOR>85</COLOR>
<MINQTY>4</MINQTY>
<NOTIFY>N</NOTIFY>
<WANTEDSHOW>N</WANTEDSHOW>
<CONDITION></CONDITION>
<WANTEDLISTID>REPLACEME</WANTEDLISTID>
</ITEM>
<ITEM>
<ITEMTYPE>P</ITEMTYPE>
<ITEMID>2540</ITEMID>
<COLOR>85</COLOR>
<MINQTY>4</MINQTY>
<NOTIFY>N</NOTIFY>
<WANTEDSHOW>N</WANTEDSHOW>
<CONDITION></CONDITION>
<WANTEDLISTID>REPLACEME</WANTEDLISTID>
</ITEM>
<ITEM>
<ITEMTYPE>P</ITEMTYPE>
<ITEMID>61409</ITEMID>
<COLOR>85</COLOR>
<MINQTY>4</MINQTY>
<NOTIFY>N</NOTIFY>
<WANTEDSHOW>N</WANTEDSHOW>
<CONDITION></CONDITION>
<WANTEDLISTID>REPLACEME</WANTEDLISTID>
</ITEM>
<ITEM>
<ITEMTYPE>P</ITEMTYPE>
<ITEMID>3795</ITEMID>
<COLOR>85</COLOR>
<MINQTY>5</MINQTY>
<NOTIFY>N</NOTIFY>
<WANTEDSHOW>N</WANTEDSHOW>
<CONDITION></CONDITION>
<WANTEDLISTID>REPLACEME</WANTEDLISTID>
</ITEM>
<ITEM>
<ITEMTYPE>P</ITEMTYPE>
<ITEMID>3941</ITEMID>
<COLOR>85</COLOR>
<MINQTY>4</MINQTY>
<NOTIFY>N</NOTIFY>
<WANTEDSHOW>N</WANTEDSHOW>
<CONDITION></CONDITION>
<WANTEDLISTID>REPLACEME</WANTEDLISTID>
</ITEM>
<ITEM>
<ITEMTYPE>P</ITEMTYPE>
<ITEMID>3020</ITEMID>
<COLOR>86</COLOR>
<MINQTY>6</MINQTY>
<NOTIFY>N</NOTIFY>
<WANTEDSHOW>N</WANTEDSHOW>
<CONDITION></CONDITION>
<WANTEDLISTID>REPLACEME</WANTEDLISTID>
</ITEM>
<ITEM>
<ITEMTYPE>P</ITEMTYPE>
<ITEMID>3068b</ITEMID>
<COLOR>69</COLOR>
<MINQTY>8</MINQTY>
<NOTIFY>N</NOTIFY>
<WANTEDSHOW>N</WANTEDSHOW>
<CONDITION></CONDITION>
<WANTEDLISTID>REPLACEME</WANTEDLISTID>
</ITEM>
<ITEM>
<ITEMTYPE>P</ITEMTYPE>
<ITEMID>3895</ITEMID>
<COLOR>85</COLOR>
<MINQTY>1</MINQTY>
<NOTIFY>N</NOTIFY>
<WANTEDSHOW>N</WANTEDSHOW>
<CONDITION></CONDITION>
<WANTEDLISTID>REPLACEME</WANTEDLISTID>
</ITEM>
<ITEM>
<ITEMTYPE>P</ITEMTYPE>
<ITEMID>91988</ITEMID>
<COLOR>85</COLOR>
<MINQTY>1</MINQTY>
<NOTIFY>N</NOTIFY>
<WANTEDSHOW>N</WANTEDSHOW>
<CONDITION></CONDITION>
<WANTEDLISTID>REPLACEME</WANTEDLISTID>
</ITEM>
<ITEM>
<ITEMTYPE>P</ITEMTYPE>
<ITEMID>2877</ITEMID>
<COLOR>85</COLOR>
<MINQTY>7</MINQTY>
<NOTIFY>N</NOTIFY>
<WANTEDSHOW>N</WANTEDSHOW>
<CONDITION></CONDITION>
<WANTEDLISTID>REPLACEME</WANTEDLISTID>
</ITEM>
<ITEM>
<ITEMTYPE>P</ITEMTYPE>
<ITEMID>32002</ITEMID>
<COLOR>85</COLOR>
<MINQTY>6</MINQTY>
<NOTIFY>N</NOTIFY>
<WANTEDSHOW>N</WANTEDSHOW>
<CONDITION></CONDITION>
<WANTEDLISTID>REPLACEME</WANTEDLISTID>
</ITEM>
<ITEM>
<ITEMTYPE>P</ITEMTYPE>
<ITEMID>3794</ITEMID>
<COLOR>1</COLOR>
<MINQTY>2</MINQTY>
<NOTIFY>N</NOTIFY>
<WANTEDSHOW>N</WANTEDSHOW>
<CONDITION></CONDITION>
<WANTEDLISTID>REPLACEME</WANTEDLISTID>
</ITEM>
<ITEM>
<ITEMTYPE>P</ITEMTYPE>
<ITEMID>2585</ITEMID>
<COLOR>86</COLOR>
<MINQTY>1</MINQTY>
<NOTIFY>N</NOTIFY>
<WANTEDSHOW>N</WANTEDSHOW>
<CONDITION></CONDITION>
<WANTEDLISTID>REPLACEME</WANTEDLISTID>
</ITEM>
<ITEM>
<ITEMTYPE>P</ITEMTYPE>
<ITEMID>3794</ITEMID>
<COLOR>85</COLOR>
<MINQTY>22</MINQTY>
<NOTIFY>N</NOTIFY>
<WANTEDSHOW>N</WANTEDSHOW>
<CONDITION></CONDITION>
<WANTEDLISTID>REPLACEME</WANTEDLISTID>
</ITEM>
<ITEM>
<ITEMTYPE>P</ITEMTYPE>
<ITEMID>3024</ITEMID>
<COLOR>1</COLOR>
<MINQTY>8</MINQTY>
<NOTIFY>N</NOTIFY>
<WANTEDSHOW>N</WANTEDSHOW>
<CONDITION></CONDITION>
<WANTEDLISTID>REPLACEME</WANTEDLISTID>
</ITEM>
<ITEM>
<ITEMTYPE>P</ITEMTYPE>
<ITEMID>3659</ITEMID>
<COLOR>69</COLOR>
<MINQTY>4</MINQTY>
<NOTIFY>N</NOTIFY>
<WANTEDSHOW>N</WANTEDSHOW>
<CONDITION></CONDITION>
<WANTEDLISTID>REPLACEME</WANTEDLISTID>
</ITEM>
<ITEM>
<ITEMTYPE>P</ITEMTYPE>
<ITEMID>2420</ITEMID>
<COLOR>88</COLOR>
<MINQTY>8</MINQTY>
<NOTIFY>N</NOTIFY>
<WANTEDSHOW>N</WANTEDSHOW>
<CONDITION></CONDITION>
<WANTEDLISTID>REPLACEME</WANTEDLISTID>
</ITEM>
<ITEM>
<ITEMTYPE>P</ITEMTYPE>
<ITEMID>3045</ITEMID>
<COLOR>69</COLOR>
<MINQTY>12</MINQTY>
<NOTIFY>N</NOTIFY>
<WANTEDSHOW>N</WANTEDSHOW>
<CONDITION></CONDITION>
<WANTEDLISTID>REPLACEME</WANTEDLISTID>
</ITEM>
<ITEM>
<ITEMTYPE>P</ITEMTYPE>
<ITEMID>3024</ITEMID>
<COLOR>69</COLOR>
<MINQTY>18</MINQTY>
<NOTIFY>N</NOTIFY>
<WANTEDSHOW>N</WANTEDSHOW>
<CONDITION></CONDITION>
<WANTEDLISTID>REPLACEME</WANTEDLISTID>
</ITEM>
<ITEM>
<ITEMTYPE>P</ITEMTYPE>
<ITEMID>54200</ITEMID>
<COLOR>85</COLOR>
<MINQTY>17</MINQTY>
<NOTIFY>N</NOTIFY>
<WANTEDSHOW>N</WANTEDSHOW>
<CONDITION></CONDITION>
<WANTEDLISTID>REPLACEME</WANTEDLISTID>
</ITEM>
<ITEM>
<ITEMTYPE>P</ITEMTYPE>
<ITEMID>3794</ITEMID>
<COLOR>69</COLOR>
<MINQTY>8</MINQTY>
<NOTIFY>N</NOTIFY>
<WANTEDSHOW>N</WANTEDSHOW>
<CONDITION></CONDITION>
<WANTEDLISTID>REPLACEME</WANTEDLISTID>
</ITEM>
<ITEM>
<ITEMTYPE>P</ITEMTYPE>
<ITEMID>41747</ITEMID>
<COLOR>69</COLOR>
<MINQTY>6</MINQTY>
<NOTIFY>N</NOTIFY>
<WANTEDSHOW>N</WANTEDSHOW>
<CONDITION></CONDITION>
<WANTEDLISTID>REPLACEME</WANTEDLISTID>
</ITEM>
<ITEM>
<ITEMTYPE>P</ITEMTYPE>
<ITEMID>41748</ITEMID>
<COLOR>69</COLOR>
<MINQTY>6</MINQTY>
<NOTIFY>N</NOTIFY>
<WANTEDSHOW>N</WANTEDSHOW>
<CONDITION></CONDITION>
<WANTEDLISTID>REPLACEME</WANTEDLISTID>
</ITEM>
<ITEM>
<ITEMTYPE>P</ITEMTYPE>
<ITEMID>47455</ITEMID>
<COLOR>85</COLOR>
<MINQTY>4</MINQTY>
<NOTIFY>N</NOTIFY>
<WANTEDSHOW>N</WANTEDSHOW>
<CONDITION></CONDITION>
<WANTEDLISTID>REPLACEME</WANTEDLISTID>
</ITEM>
<ITEM>
<ITEMTYPE>P</ITEMTYPE>
<ITEMID>48170</ITEMID>
<COLOR>85</COLOR>
<MINQTY>4</MINQTY>
<NOTIFY>N</NOTIFY>
<WANTEDSHOW>N</WANTEDSHOW>
<CONDITION></CONDITION>
<WANTEDLISTID>REPLACEME</WANTEDLISTID>
</ITEM>
<ITEM>
<ITEMTYPE>P</ITEMTYPE>
<ITEMID>2654</ITEMID>
<COLOR>85</COLOR>
<MINQTY>4</MINQTY>
<NOTIFY>N</NOTIFY>
<WANTEDSHOW>N</WANTEDSHOW>
<CONDITION></CONDITION>
<WANTEDLISTID>REPLACEME</WANTEDLISTID>
</ITEM>
<ITEM>
<ITEMTYPE>P</ITEMTYPE>
<ITEMID>44567</ITEMID>
<COLOR>85</COLOR>
<MINQTY>4</MINQTY>
<NOTIFY>N</NOTIFY>
<WANTEDSHOW>N</WANTEDSHOW>
<CONDITION></CONDITION>
<WANTEDLISTID>REPLACEME</WANTEDLISTID>
</ITEM>
<ITEM>
<ITEMTYPE>P</ITEMTYPE>
<ITEMID>50950</ITEMID>
<COLOR>85</COLOR>
<MINQTY>12</MINQTY>
<NOTIFY>N</NOTIFY>
<WANTEDSHOW>N</WANTEDSHOW>
<CONDITION></CONDITION>
<WANTEDLISTID>REPLACEME</WANTEDLISTID>
</ITEM>
<ITEM>
<ITEMTYPE>P</ITEMTYPE>
<ITEMID>60471</ITEMID>
<COLOR>86</COLOR>
<MINQTY>4</MINQTY>
<NOTIFY>N</NOTIFY>
<WANTEDSHOW>N</WANTEDSHOW>
<CONDITION></CONDITION>
<WANTEDLISTID>REPLACEME</WANTEDLISTID>
</ITEM>
<ITEM>
<ITEMTYPE>P</ITEMTYPE>
<ITEMID>86208</ITEMID>
<COLOR>85</COLOR>
<MINQTY>8</MINQTY>
<NOTIFY>N</NOTIFY>
<WANTEDSHOW>N</WANTEDSHOW>
<CONDITION></CONDITION>
<WANTEDLISTID>REPLACEME</WANTEDLISTID>
</ITEM>
<ITEM>
<ITEMTYPE>P</ITEMTYPE>
<ITEMID>47905</ITEMID>
<COLOR>85</COLOR>
<MINQTY>10</MINQTY>
<NOTIFY>N</NOTIFY>
<WANTEDSHOW>N</WANTEDSHOW>
<CONDITION></CONDITION>
<WANTEDLISTID>REPLACEME</WANTEDLISTID>
</ITEM>
<ITEM>
<ITEMTYPE>P</ITEMTYPE>
<ITEMID>3070b</ITEMID>
<COLOR>85</COLOR>
<MINQTY>11</MINQTY>
<NOTIFY>N</NOTIFY>
<WANTEDSHOW>N</WANTEDSHOW>
<CONDITION></CONDITION>
<WANTEDLISTID>REPLACEME</WANTEDLISTID>
</ITEM>
<ITEM>
<ITEMTYPE>P</ITEMTYPE>
<ITEMID>4287</ITEMID>
<COLOR>85</COLOR>
<MINQTY>10</MINQTY>
<NOTIFY>N</NOTIFY>
<WANTEDSHOW>N</WANTEDSHOW>
<CONDITION></CONDITION>
<WANTEDLISTID>REPLACEME</WANTEDLISTID>
</ITEM>
<ITEM>
<ITEMTYPE>P</ITEMTYPE>
<ITEMID>3062b</ITEMID>
<COLOR>3</COLOR>
<MINQTY>8</MINQTY>
<NOTIFY>N</NOTIFY>
<WANTEDSHOW>N</WANTEDSHOW>
<CONDITION></CONDITION>
<WANTEDLISTID>REPLACEME</WANTEDLISTID>
</ITEM>
<ITEM>
<ITEMTYPE>P</ITEMTYPE>
<ITEMID>3004</ITEMID>
<COLOR>1</COLOR>
<MINQTY>1</MINQTY>
<NOTIFY>N</NOTIFY>
<WANTEDSHOW>N</WANTEDSHOW>
<CONDITION></CONDITION>
<WANTEDLISTID>REPLACEME</WANTEDLISTID>
</ITEM>
<ITEM>
<ITEMTYPE>P</ITEMTYPE>
<ITEMID>44728</ITEMID>
<COLOR>85</COLOR>
<MINQTY>4</MINQTY>
<NOTIFY>N</NOTIFY>
<WANTEDSHOW>N</WANTEDSHOW>
<CONDITION></CONDITION>
<WANTEDLISTID>REPLACEME</WANTEDLISTID>
</ITEM>
<ITEM>
<ITEMTYPE>P</ITEMTYPE>
<ITEMID>4073</ITEMID>
<COLOR>12</COLOR>
<MINQTY>2</MINQTY>
<NOTIFY>N</NOTIFY>
<WANTEDSHOW>N</WANTEDSHOW>
<CONDITION></CONDITION>
<WANTEDLISTID>REPLACEME</WANTEDLISTID>
</ITEM>
<ITEM>
<ITEMTYPE>P</ITEMTYPE>
<ITEMID>3069b</ITEMID>
<COLOR>88</COLOR>
<MINQTY>8</MINQTY>
<NOTIFY>N</NOTIFY>
<WANTEDSHOW>N</WANTEDSHOW>
<CONDITION></CONDITION>
<WANTEDLISTID>REPLACEME</WANTEDLISTID>
</ITEM>
<ITEM>
<ITEMTYPE>P</ITEMTYPE>
<ITEMID>98138</ITEMID>
<COLOR>20</COLOR>
<MINQTY>1</MINQTY>
<NOTIFY>N</NOTIFY>
<WANTEDSHOW>N</WANTEDSHOW>
<CONDITION></CONDITION>
<WANTEDLISTID>REPLACEME</WANTEDLISTID>
</ITEM>
<ITEM>
<ITEMTYPE>P</ITEMTYPE>
<ITEMID>64567</ITEMID>
<COLOR>86</COLOR>
<MINQTY>1</MINQTY>
<NOTIFY>N</NOTIFY>
<WANTEDSHOW>N</WANTEDSHOW>
<CONDITION></CONDITION>
<WANTEDLISTID>REPLACEME</WANTEDLISTID>
</ITEM>
<ITEM>
<ITEMTYPE>P</ITEMTYPE>
<ITEMID>60849</ITEMID>
<COLOR>86</COLOR>
<MINQTY>1</MINQTY>
<NOTIFY>N</NOTIFY>
<WANTEDSHOW>N</WANTEDSHOW>
<CONDITION></CONDITION>
<WANTEDLISTID>REPLACEME</WANTEDLISTID>
</ITEM>
<ITEM>
<ITEMTYPE>P</ITEMTYPE>
<ITEMID>3001</ITEMID>
<COLOR>69</COLOR>
<MINQTY>2</MINQTY>
<NOTIFY>N</NOTIFY>
<WANTEDSHOW>N</WANTEDSHOW>
<CONDITION></CONDITION>
<WANTEDLISTID>REPLACEME</WANTEDLISTID>
</ITEM>
<ITEM>
<ITEMTYPE>P</ITEMTYPE>
<ITEMID>3070b</ITEMID>
<COLOR>12</COLOR>
<MINQTY>2</MINQTY>
<NOTIFY>N</NOTIFY>
<WANTEDSHOW>N</WANTEDSHOW>
<CONDITION></CONDITION>
<WANTEDLISTID>REPLACEME</WANTEDLISTID>
</ITEM>
<ITEM>
<ITEMTYPE>P</ITEMTYPE>
<ITEMID>58846</ITEMID>
<COLOR>69</COLOR>
<MINQTY>2</MINQTY>
<NOTIFY>N</NOTIFY>
<WANTEDSHOW>N</WANTEDSHOW>
<CONDITION></CONDITION>
<WANTEDLISTID>REPLACEME</WANTEDLISTID>
</ITEM>
<ITEM>
<ITEMTYPE>P</ITEMTYPE>
<ITEMID>61252</ITEMID>
<COLOR>85</COLOR>
<MINQTY>4</MINQTY>
<NOTIFY>N</NOTIFY>
<WANTEDSHOW>N</WANTEDSHOW>
<CONDITION></CONDITION>
<WANTEDLISTID>REPLACEME</WANTEDLISTID>
</ITEM>
<ITEM>
<ITEMTYPE>P</ITEMTYPE>
<ITEMID>2357</ITEMID>
<COLOR>85</COLOR>
<MINQTY>1</MINQTY>
<NOTIFY>N</NOTIFY>
<WANTEDSHOW>N</WANTEDSHOW>
<CONDITION></CONDITION>
<WANTEDLISTID>REPLACEME</WANTEDLISTID>
</ITEM>
<ITEM>
<ITEMTYPE>P</ITEMTYPE>
<ITEMID>3040</ITEMID>
<COLOR>88</COLOR>
<MINQTY>4</MINQTY>
<NOTIFY>N</NOTIFY>
<WANTEDSHOW>N</WANTEDSHOW>
<CONDITION></CONDITION>
<WANTEDLISTID>REPLACEME</WANTEDLISTID>
</ITEM>
<ITEM>
<ITEMTYPE>P</ITEMTYPE>
<ITEMID>3004</ITEMID>
<COLOR>88</COLOR>
<MINQTY>4</MINQTY>
<NOTIFY>N</NOTIFY>
<WANTEDSHOW>N</WANTEDSHOW>
<CONDITION></CONDITION>
<WANTEDLISTID>REPLACEME</WANTEDLISTID>
</ITEM>
<ITEM>
<ITEMTYPE>P</ITEMTYPE>
<ITEMID>2555</ITEMID>
<COLOR>85</COLOR>
<MINQTY>15</MINQTY>
<NOTIFY>N</NOTIFY>
<WANTEDSHOW>N</WANTEDSHOW>
<CONDITION></CONDITION>
<WANTEDLISTID>REPLACEME</WANTEDLISTID>
</ITEM>
<ITEM>
<ITEMTYPE>P</ITEMTYPE>
<ITEMID>45677</ITEMID>
<COLOR>85</COLOR>
<MINQTY>2</MINQTY>
<NOTIFY>N</NOTIFY>
<WANTEDSHOW>N</WANTEDSHOW>
<CONDITION></CONDITION>
<WANTEDLISTID>REPLACEME</WANTEDLISTID>
</ITEM>
<ITEM>
<ITEMTYPE>P</ITEMTYPE>
<ITEMID>3020</ITEMID>
<COLOR>69</COLOR>
<MINQTY>2</MINQTY>
<NOTIFY>N</NOTIFY>
<WANTEDSHOW>N</WANTEDSHOW>
<CONDITION></CONDITION>
<WANTEDLISTID>REPLACEME</WANTEDLISTID>
</ITEM>
<ITEM>
<ITEMTYPE>P</ITEMTYPE>
<ITEMID>43722</ITEMID>
<COLOR>85</COLOR>
<MINQTY>1</MINQTY>
<NOTIFY>N</NOTIFY>
<WANTEDSHOW>N</WANTEDSHOW>
<CONDITION></CONDITION>
<WANTEDLISTID>REPLACEME</WANTEDLISTID>
</ITEM>
<ITEM>
<ITEMTYPE>P</ITEMTYPE>
<ITEMID>30374</ITEMID>
<COLOR>85</COLOR>
<MINQTY>2</MINQTY>
<NOTIFY>N</NOTIFY>
<WANTEDSHOW>N</WANTEDSHOW>
<CONDITION></CONDITION>
<WANTEDLISTID>REPLACEME</WANTEDLISTID>
</ITEM>
<ITEM>
<ITEMTYPE>P</ITEMTYPE>
<ITEMID>43723</ITEMID>
<COLOR>85</COLOR>
<MINQTY>1</MINQTY>
<NOTIFY>N</NOTIFY>
<WANTEDSHOW>N</WANTEDSHOW>
<CONDITION></CONDITION>
<WANTEDLISTID>REPLACEME</WANTEDLISTID>
</ITEM>
<ITEM>
<ITEMTYPE>P</ITEMTYPE>
<ITEMID>3003</ITEMID>
<COLOR>69</COLOR>
<MINQTY>1</MINQTY>
<NOTIFY>N</NOTIFY>
<WANTEDSHOW>N</WANTEDSHOW>
<CONDITION></CONDITION>
<WANTEDLISTID>REPLACEME</WANTEDLISTID>
</ITEM>
<ITEM>
<ITEMTYPE>P</ITEMTYPE>
<ITEMID>42022</ITEMID>
<COLOR>88</COLOR>
<MINQTY>4</MINQTY>
<NOTIFY>N</NOTIFY>
<WANTEDSHOW>N</WANTEDSHOW>
<CONDITION></CONDITION>
<WANTEDLISTID>REPLACEME</WANTEDLISTID>
</ITEM>
<ITEM>
<ITEMTYPE>P</ITEMTYPE>
<ITEMID>30350</ITEMID>
<COLOR>85</COLOR>
<MINQTY>1</MINQTY>
<NOTIFY>N</NOTIFY>
<WANTEDSHOW>N</WANTEDSHOW>
<CONDITION></CONDITION>
<WANTEDLISTID>REPLACEME</WANTEDLISTID>
</ITEM>
<ITEM>
<ITEMTYPE>P</ITEMTYPE>
<ITEMID>3665</ITEMID>
<COLOR>85</COLOR>
<MINQTY>4</MINQTY>
<NOTIFY>N</NOTIFY>
<WANTEDSHOW>N</WANTEDSHOW>
<CONDITION></CONDITION>
<WANTEDLISTID>REPLACEME</WANTEDLISTID>
</ITEM>
<ITEM>
<ITEMTYPE>P</ITEMTYPE>
<ITEMID>54200</ITEMID>
<COLOR>88</COLOR>
<MINQTY>2</MINQTY>
<NOTIFY>N</NOTIFY>
<WANTEDSHOW>N</WANTEDSHOW>
<CONDITION></CONDITION>
<WANTEDLISTID>REPLACEME</WANTEDLISTID>
</ITEM>
<ITEM>
<ITEMTYPE>P</ITEMTYPE>
<ITEMID>3680c02</ITEMID>
<COLOR>11</COLOR>
<MINQTY>1</MINQTY>
<NOTIFY>N</NOTIFY>
<WANTEDSHOW>N</WANTEDSHOW>
<CONDITION></CONDITION>
<WANTEDLISTID>REPLACEME</WANTEDLISTID>
</ITEM>
<ITEM>
<ITEMTYPE>P</ITEMTYPE>
<ITEMID>2420</ITEMID>
<COLOR>69</COLOR>
<MINQTY>2</MINQTY>
<NOTIFY>N</NOTIFY>
<WANTEDSHOW>N</WANTEDSHOW>
<CONDITION></CONDITION>
<WANTEDLISTID>REPLACEME</WANTEDLISTID>
</ITEM>
<ITEM>
<ITEMTYPE>P</ITEMTYPE>
<ITEMID>4073</ITEMID>
<COLOR>95</COLOR>
<MINQTY>3</MINQTY>
<NOTIFY>N</NOTIFY>
<WANTEDSHOW>N</WANTEDSHOW>
<CONDITION></CONDITION>
<WANTEDLISTID>REPLACEME</WANTEDLISTID>
</ITEM>
<ITEM>
<ITEMTYPE>P</ITEMTYPE>
<ITEMID>3660</ITEMID>
<COLOR>85</COLOR>
<MINQTY>2</MINQTY>
<NOTIFY>N</NOTIFY>
<WANTEDSHOW>N</WANTEDSHOW>
<CONDITION></CONDITION>
<WANTEDLISTID>REPLACEME</WANTEDLISTID>
</ITEM>
<ITEM>
<ITEMTYPE>P</ITEMTYPE>
<ITEMID>2445</ITEMID>
<COLOR>85</COLOR>
<MINQTY>1</MINQTY>
<NOTIFY>N</NOTIFY>
<WANTEDSHOW>N</WANTEDSHOW>
<CONDITION></CONDITION>
<WANTEDLISTID>REPLACEME</WANTEDLISTID>
</ITEM>
<ITEM>
<ITEMTYPE>P</ITEMTYPE>
<ITEMID>3832</ITEMID>
<COLOR>85</COLOR>
<MINQTY>1</MINQTY>
<NOTIFY>N</NOTIFY>
<WANTEDSHOW>N</WANTEDSHOW>
<CONDITION></CONDITION>
<WANTEDLISTID>REPLACEME</WANTEDLISTID>
</ITEM>
<ITEM>
<ITEMTYPE>P</ITEMTYPE>
<ITEMID>3032</ITEMID>
<COLOR>85</COLOR>
<MINQTY>2</MINQTY>
<NOTIFY>N</NOTIFY>
<WANTEDSHOW>N</WANTEDSHOW>
<CONDITION></CONDITION>
<WANTEDLISTID>REPLACEME</WANTEDLISTID>
</ITEM>
<ITEM>
<ITEMTYPE>P</ITEMTYPE>
<ITEMID>3035</ITEMID>
<COLOR>85</COLOR>
<MINQTY>1</MINQTY>
<NOTIFY>N</NOTIFY>
<WANTEDSHOW>N</WANTEDSHOW>
<CONDITION></CONDITION>
<WANTEDLISTID>REPLACEME</WANTEDLISTID>
</ITEM>
<ITEM>
<ITEMTYPE>P</ITEMTYPE>
<ITEMID>3039pb41</ITEMID>
<COLOR>1</COLOR>
<MINQTY>1</MINQTY>
<NOTIFY>N</NOTIFY>
<WANTEDSHOW>N</WANTEDSHOW>
<CONDITION></CONDITION>
<WANTEDLISTID>REPLACEME</WANTEDLISTID>
</ITEM>
<ITEM>
<ITEMTYPE>P</ITEMTYPE>
<ITEMID>3023</ITEMID>
<COLOR>86</COLOR>
<MINQTY>4</MINQTY>
<NOTIFY>N</NOTIFY>
<WANTEDSHOW>N</WANTEDSHOW>
<CONDITION></CONDITION>
<WANTEDLISTID>REPLACEME</WANTEDLISTID>
</ITEM>
<ITEM>
<ITEMTYPE>P</ITEMTYPE>
<ITEMID>48336</ITEMID>
<COLOR>86</COLOR>
<MINQTY>3</MINQTY>
<NOTIFY>N</NOTIFY>
<WANTEDSHOW>N</WANTEDSHOW>
<CONDITION></CONDITION>
<WANTEDLISTID>REPLACEME</WANTEDLISTID>
</ITEM>
<ITEM>
<ITEMTYPE>P</ITEMTYPE>
<ITEMID>54200</ITEMID>
<COLOR>17</COLOR>
<MINQTY>2</MINQTY>
<NOTIFY>N</NOTIFY>
<WANTEDSHOW>N</WANTEDSHOW>
<CONDITION></CONDITION>
<WANTEDLISTID>REPLACEME</WANTEDLISTID>
</ITEM>
<ITEM>
<ITEMTYPE>P</ITEMTYPE>
<ITEMID>93274</ITEMID>
<COLOR>86</COLOR>
<MINQTY>2</MINQTY>
<NOTIFY>N</NOTIFY>
<WANTEDSHOW>N</WANTEDSHOW>
<CONDITION></CONDITION>
<WANTEDLISTID>REPLACEME</WANTEDLISTID>
</ITEM>
<ITEM>
<ITEMTYPE>P</ITEMTYPE>
<ITEMID>3032</ITEMID>
<COLOR>86</COLOR>
<MINQTY>1</MINQTY>
<NOTIFY>N</NOTIFY>
<WANTEDSHOW>N</WANTEDSHOW>
<CONDITION></CONDITION>
<WANTEDLISTID>REPLACEME</WANTEDLISTID>
</ITEM>
<ITEM>
<ITEMTYPE>P</ITEMTYPE>
<ITEMID>3069bpx19</ITEMID>
<COLOR>86</COLOR>
<MINQTY>1</MINQTY>
<NOTIFY>N</NOTIFY>
<WANTEDSHOW>N</WANTEDSHOW>
<CONDITION></CONDITION>
<WANTEDLISTID>REPLACEME</WANTEDLISTID>
</ITEM>
<ITEM>
<ITEMTYPE>P</ITEMTYPE>
<ITEMID>3070bp07</ITEMID>
<COLOR>86</COLOR>
<MINQTY>2</MINQTY>
<NOTIFY>N</NOTIFY>
<WANTEDSHOW>N</WANTEDSHOW>
<CONDITION></CONDITION>
<WANTEDLISTID>REPLACEME</WANTEDLISTID>
</ITEM>
<ITEM>
<ITEMTYPE>P</ITEMTYPE>
<ITEMID>4150ps4</ITEMID>
<COLOR>86</COLOR>
<MINQTY>2</MINQTY>
<NOTIFY>N</NOTIFY>
<WANTEDSHOW>N</WANTEDSHOW>
<CONDITION></CONDITION>
<WANTEDLISTID>REPLACEME</WANTEDLISTID>
</ITEM>
<ITEM>
<ITEMTYPE>P</ITEMTYPE>
<ITEMID>3069bpc1</ITEMID>
<COLOR>85</COLOR>
<MINQTY>2</MINQTY>
<NOTIFY>N</NOTIFY>
<WANTEDSHOW>N</WANTEDSHOW>
<CONDITION></CONDITION>
<WANTEDLISTID>REPLACEME</WANTEDLISTID>
</ITEM>
<ITEM>
<ITEMTYPE>P</ITEMTYPE>
<ITEMID>32028</ITEMID>
<COLOR>85</COLOR>
<MINQTY>1</MINQTY>
<NOTIFY>N</NOTIFY>
<WANTEDSHOW>N</WANTEDSHOW>
<CONDITION></CONDITION>
<WANTEDLISTID>REPLACEME</WANTEDLISTID>
</ITEM>
<ITEM>
<ITEMTYPE>P</ITEMTYPE>
<ITEMID>4216</ITEMID>
<COLOR>1</COLOR>
<MINQTY>1</MINQTY>
<NOTIFY>N</NOTIFY>
<WANTEDSHOW>N</WANTEDSHOW>
<CONDITION></CONDITION>
<WANTEDLISTID>REPLACEME</WANTEDLISTID>
</ITEM>
<ITEM>
<ITEMTYPE>P</ITEMTYPE>
<ITEMID>87620</ITEMID>
<COLOR>85</COLOR>
<MINQTY>6</MINQTY>
<NOTIFY>N</NOTIFY>
<WANTEDSHOW>N</WANTEDSHOW>
<CONDITION></CONDITION>
<WANTEDLISTID>REPLACEME</WANTEDLISTID>
</ITEM>
<ITEM>
<ITEMTYPE>P</ITEMTYPE>
<ITEMID>98138</ITEMID>
<COLOR>95</COLOR>
<MINQTY>1</MINQTY>
<NOTIFY>N</NOTIFY>
<WANTEDSHOW>N</WANTEDSHOW>
<CONDITION></CONDITION>
<WANTEDLISTID>REPLACEME</WANTEDLISTID>
</ITEM>
<ITEM>
<ITEMTYPE>P</ITEMTYPE>
<ITEMID>2555</ITEMID>
<COLOR>1</COLOR>
<MINQTY>2</MINQTY>
<NOTIFY>N</NOTIFY>
<WANTEDSHOW>N</WANTEDSHOW>
<CONDITION></CONDITION>
<WANTEDLISTID>REPLACEME</WANTEDLISTID>
</ITEM>
<ITEM>
<ITEMTYPE>P</ITEMTYPE>
<ITEMID>48336</ITEMID>
<COLOR>1</COLOR>
<MINQTY>2</MINQTY>
<NOTIFY>N</NOTIFY>
<WANTEDSHOW>N</WANTEDSHOW>
<CONDITION></CONDITION>
<WANTEDLISTID>REPLACEME</WANTEDLISTID>
</ITEM>
<ITEM>
<ITEMTYPE>P</ITEMTYPE>
<ITEMID>3068b</ITEMID>
<COLOR>88</COLOR>
<MINQTY>1</MINQTY>
<NOTIFY>N</NOTIFY>
<WANTEDSHOW>N</WANTEDSHOW>
<CONDITION></CONDITION>
<WANTEDLISTID>REPLACEME</WANTEDLISTID>
</ITEM>
<ITEM>
<ITEMTYPE>P</ITEMTYPE>
<ITEMID>3003</ITEMID>
<COLOR>86</COLOR>
<MINQTY>1</MINQTY>
<NOTIFY>N</NOTIFY>
<WANTEDSHOW>N</WANTEDSHOW>
<CONDITION></CONDITION>
<WANTEDLISTID>REPLACEME</WANTEDLISTID>
</ITEM>
<ITEM>
<ITEMTYPE>P</ITEMTYPE>
<ITEMID>2555</ITEMID>
<COLOR>86</COLOR>
<MINQTY>2</MINQTY>
<NOTIFY>N</NOTIFY>
<WANTEDSHOW>N</WANTEDSHOW>
<CONDITION></CONDITION>
<WANTEDLISTID>REPLACEME</WANTEDLISTID>
</ITEM>
<ITEM>
<ITEMTYPE>P</ITEMTYPE>
<ITEMID>3008</ITEMID>
<COLOR>69</COLOR>
<MINQTY>2</MINQTY>
<NOTIFY>N</NOTIFY>
<WANTEDSHOW>N</WANTEDSHOW>
<CONDITION></CONDITION>
<WANTEDLISTID>REPLACEME</WANTEDLISTID>
</ITEM>
<ITEM>
<ITEMTYPE>P</ITEMTYPE>
<ITEMID>3666</ITEMID>
<COLOR>85</COLOR>
<MINQTY>2</MINQTY>
<NOTIFY>N</NOTIFY>
<WANTEDSHOW>N</WANTEDSHOW>
<CONDITION></CONDITION>
<WANTEDLISTID>REPLACEME</WANTEDLISTID>
</ITEM>
<ITEM>
<ITEMTYPE>P</ITEMTYPE>
<ITEMID>3039</ITEMID>
<COLOR>85</COLOR>
<MINQTY>6</MINQTY>
<NOTIFY>N</NOTIFY>
<WANTEDSHOW>N</WANTEDSHOW>
<CONDITION></CONDITION>
<WANTEDLISTID>REPLACEME</WANTEDLISTID>
</ITEM>
<ITEM>
<ITEMTYPE>P</ITEMTYPE>
<ITEMID>2431</ITEMID>
<COLOR>85</COLOR>
<MINQTY>4</MINQTY>
<NOTIFY>N</NOTIFY>
<WANTEDSHOW>N</WANTEDSHOW>
<CONDITION></CONDITION>
<WANTEDLISTID>REPLACEME</WANTEDLISTID>
</ITEM>
<ITEM>
<ITEMTYPE>P</ITEMTYPE>
<ITEMID>63965</ITEMID>
<COLOR>85</COLOR>
<MINQTY>2</MINQTY>
<NOTIFY>N</NOTIFY>
<WANTEDSHOW>N</WANTEDSHOW>
<CONDITION></CONDITION>
<WANTEDLISTID>REPLACEME</WANTEDLISTID>
</ITEM>
<ITEM>
<ITEMTYPE>P</ITEMTYPE>
<ITEMID>87087</ITEMID>
<COLOR>11</COLOR>
<MINQTY>2</MINQTY>
<NOTIFY>N</NOTIFY>
<WANTEDSHOW>N</WANTEDSHOW>
<CONDITION></CONDITION>
<WANTEDLISTID>REPLACEME</WANTEDLISTID>
</ITEM>
<ITEM>
<ITEMTYPE>P</ITEMTYPE>
<ITEMID>64567</ITEMID>
<COLOR>11</COLOR>
<MINQTY>2</MINQTY>
<NOTIFY>N</NOTIFY>
<WANTEDSHOW>N</WANTEDSHOW>
<CONDITION></CONDITION>
<WANTEDLISTID>REPLACEME</WANTEDLISTID>
</ITEM>
<ITEM>
<ITEMTYPE>P</ITEMTYPE>
<ITEMID>3062b</ITEMID>
<COLOR>11</COLOR>
<MINQTY>2</MINQTY>
<NOTIFY>N</NOTIFY>
<WANTEDSHOW>N</WANTEDSHOW>
<CONDITION></CONDITION>
<WANTEDLISTID>REPLACEME</WANTEDLISTID>
</ITEM>
<ITEM>
<ITEMTYPE>P</ITEMTYPE>
<ITEMID>3023</ITEMID>
<COLOR>11</COLOR>
<MINQTY>2</MINQTY>
<NOTIFY>N</NOTIFY>
<WANTEDSHOW>N</WANTEDSHOW>
<CONDITION></CONDITION>
<WANTEDLISTID>REPLACEME</WANTEDLISTID>
</ITEM>
<ITEM>
<ITEMTYPE>P</ITEMTYPE>
<ITEMID>2877</ITEMID>
<COLOR>11</COLOR>
<MINQTY>1</MINQTY>
<NOTIFY>N</NOTIFY>
<WANTEDSHOW>N</WANTEDSHOW>
<CONDITION></CONDITION>
<WANTEDLISTID>REPLACEME</WANTEDLISTID>
</ITEM>
<ITEM>
<ITEMTYPE>P</ITEMTYPE>
<ITEMID>98138</ITEMID>
<COLOR>86</COLOR>
<MINQTY>2</MINQTY>
<NOTIFY>N</NOTIFY>
<WANTEDSHOW>N</WANTEDSHOW>
<CONDITION></CONDITION>
<WANTEDLISTID>REPLACEME</WANTEDLISTID>
</ITEM>
<ITEM>
<ITEMTYPE>P</ITEMTYPE>
<ITEMID>61678</ITEMID>
<COLOR>85</COLOR>
<MINQTY>2</MINQTY>
<NOTIFY>N</NOTIFY>
<WANTEDSHOW>N</WANTEDSHOW>
<CONDITION></CONDITION>
<WANTEDLISTID>REPLACEME</WANTEDLISTID>
</ITEM>
<ITEM>
<ITEMTYPE>P</ITEMTYPE>
<ITEMID>3700</ITEMID>
<COLOR>85</COLOR>
<MINQTY>4</MINQTY>
<NOTIFY>N</NOTIFY>
<WANTEDSHOW>N</WANTEDSHOW>
<CONDITION></CONDITION>
<WANTEDLISTID>REPLACEME</WANTEDLISTID>
</ITEM>
<ITEM>
<ITEMTYPE>P</ITEMTYPE>
<ITEMID>2397</ITEMID>
<COLOR>85</COLOR>
<MINQTY>5</MINQTY>
<NOTIFY>N</NOTIFY>
<WANTEDSHOW>N</WANTEDSHOW>
<CONDITION></CONDITION>
<WANTEDLISTID>REPLACEME</WANTEDLISTID>
</ITEM>
<ITEM>
<ITEMTYPE>P</ITEMTYPE>
<ITEMID>3839b</ITEMID>
<COLOR>85</COLOR>
<MINQTY>1</MINQTY>
<NOTIFY>N</NOTIFY>
<WANTEDSHOW>N</WANTEDSHOW>
<CONDITION></CONDITION>
<WANTEDLISTID>REPLACEME</WANTEDLISTID>
</ITEM>
<ITEM>
<ITEMTYPE>P</ITEMTYPE>
<ITEMID>3069b</ITEMID>
<COLOR>1</COLOR>
<MINQTY>1</MINQTY>
<NOTIFY>N</NOTIFY>
<WANTEDSHOW>N</WANTEDSHOW>
<CONDITION></CONDITION>
<WANTEDLISTID>REPLACEME</WANTEDLISTID>
</ITEM>
<ITEM>
<ITEMTYPE>P</ITEMTYPE>
<ITEMID>3070b</ITEMID>
<COLOR>6</COLOR>
<MINQTY>2</MINQTY>
<NOTIFY>N</NOTIFY>
<WANTEDSHOW>N</WANTEDSHOW>
<CONDITION></CONDITION>
<WANTEDLISTID>REPLACEME</WANTEDLISTID>
</ITEM>
<ITEM>
<ITEMTYPE>P</ITEMTYPE>
<ITEMID>4733</ITEMID>
<COLOR>85</COLOR>
<MINQTY>2</MINQTY>
<NOTIFY>N</NOTIFY>
<WANTEDSHOW>N</WANTEDSHOW>
<CONDITION></CONDITION>
<WANTEDLISTID>REPLACEME</WANTEDLISTID>
</ITEM>
<ITEM>
<ITEMTYPE>P</ITEMTYPE>
<ITEMID>2449</ITEMID>
<COLOR>85</COLOR>
<MINQTY>2</MINQTY>
<NOTIFY>N</NOTIFY>
<WANTEDSHOW>N</WANTEDSHOW>
<CONDITION></CONDITION>
<WANTEDLISTID>REPLACEME</WANTEDLISTID>
</ITEM>
<ITEM>
<ITEMTYPE>P</ITEMTYPE>
<ITEMID>32064</ITEMID>
<COLOR>85</COLOR>
<MINQTY>3</MINQTY>
<NOTIFY>N</NOTIFY>
<WANTEDSHOW>N</WANTEDSHOW>
<CONDITION></CONDITION>
<WANTEDLISTID>REPLACEME</WANTEDLISTID>
</ITEM>
<ITEM>
<ITEMTYPE>P</ITEMTYPE>
<ITEMID>3062b</ITEMID>
<COLOR>6</COLOR>
<MINQTY>2</MINQTY>
<NOTIFY>N</NOTIFY>
<WANTEDSHOW>N</WANTEDSHOW>
<CONDITION></CONDITION>
<WANTEDLISTID>REPLACEME</WANTEDLISTID>
</ITEM>
<ITEM>
<ITEMTYPE>P</ITEMTYPE>
<ITEMID>4073</ITEMID>
<COLOR>1</COLOR>
<MINQTY>2</MINQTY>
<NOTIFY>N</NOTIFY>
<WANTEDSHOW>N</WANTEDSHOW>
<CONDITION></CONDITION>
<WANTEDLISTID>REPLACEME</WANTEDLISTID>
</ITEM>
<ITEM>
<ITEMTYPE>P</ITEMTYPE>
<ITEMID>3737</ITEMID>
<COLOR>11</COLOR>
<MINQTY>1</MINQTY>
<NOTIFY>N</NOTIFY>
<WANTEDSHOW>N</WANTEDSHOW>
<CONDITION></CONDITION>
<WANTEDLISTID>REPLACEME</WANTEDLISTID>
</ITEM>
<ITEM>
<ITEMTYPE>P</ITEMTYPE>
<ITEMID>3713</ITEMID>
<COLOR>86</COLOR>
<MINQTY>2</MINQTY>
<NOTIFY>N</NOTIFY>
<WANTEDSHOW>N</WANTEDSHOW>
<CONDITION></CONDITION>
<WANTEDLISTID>REPLACEME</WANTEDLISTID>
</ITEM>
<ITEM>
<ITEMTYPE>P</ITEMTYPE>
<ITEMID>32270</ITEMID>
<COLOR>86</COLOR>
<MINQTY>1</MINQTY>
<NOTIFY>N</NOTIFY>
<WANTEDSHOW>N</WANTEDSHOW>
<CONDITION></CONDITION>
<WANTEDLISTID>REPLACEME</WANTEDLISTID>
</ITEM>
<ITEM>
<ITEMTYPE>P</ITEMTYPE>
<ITEMID>88393</ITEMID>
<COLOR>85</COLOR>
<MINQTY>4</MINQTY>
<NOTIFY>N</NOTIFY>
<WANTEDSHOW>N</WANTEDSHOW>
<CONDITION></CONDITION>
<WANTEDLISTID>REPLACEME</WANTEDLISTID>
</ITEM>
<ITEM>
<ITEMTYPE>P</ITEMTYPE>
<ITEMID>3684</ITEMID>
<COLOR>85</COLOR>
<MINQTY>2</MINQTY>
<NOTIFY>N</NOTIFY>
<WANTEDSHOW>N</WANTEDSHOW>
<CONDITION></CONDITION>
<WANTEDLISTID>REPLACEME</WANTEDLISTID>
</ITEM>
<ITEM>
<ITEMTYPE>P</ITEMTYPE>
<ITEMID>4716</ITEMID>
<COLOR>86</COLOR>
<MINQTY>1</MINQTY>
<NOTIFY>N</NOTIFY>
<WANTEDSHOW>N</WANTEDSHOW>
<CONDITION></CONDITION>
<WANTEDLISTID>REPLACEME</WANTEDLISTID>
</ITEM>
<ITEM>
<ITEMTYPE>P</ITEMTYPE>
<ITEMID>32073</ITEMID>
<COLOR>11</COLOR>
<MINQTY>1</MINQTY>
<NOTIFY>N</NOTIFY>
<WANTEDSHOW>N</WANTEDSHOW>
<CONDITION></CONDITION>
<WANTEDLISTID>REPLACEME</WANTEDLISTID>
</ITEM>
<ITEM>
<ITEMTYPE>P</ITEMTYPE>
<ITEMID>4265c</ITEMID>
<COLOR>86</COLOR>
<MINQTY>1</MINQTY>
<NOTIFY>N</NOTIFY>
<WANTEDSHOW>N</WANTEDSHOW>
<CONDITION></CONDITION>
<WANTEDLISTID>REPLACEME</WANTEDLISTID>
</ITEM>
<ITEM>
<ITEMTYPE>P</ITEMTYPE>
<ITEMID>6589</ITEMID>
<COLOR>86</COLOR>
<MINQTY>1</MINQTY>
<NOTIFY>N</NOTIFY>
<WANTEDSHOW>N</WANTEDSHOW>
<CONDITION></CONDITION>
<WANTEDLISTID>REPLACEME</WANTEDLISTID>
</ITEM>
<ITEM>
<ITEMTYPE>P</ITEMTYPE>
<ITEMID>4032</ITEMID>
<COLOR>85</COLOR>
<MINQTY>22</MINQTY>
<NOTIFY>N</NOTIFY>
<WANTEDSHOW>N</WANTEDSHOW>
<CONDITION></CONDITION>
<WANTEDLISTID>REPLACEME</WANTEDLISTID>
</ITEM>
<ITEM>
<ITEMTYPE>P</ITEMTYPE>
<ITEMID>4032</ITEMID>
<COLOR>5</COLOR>
<MINQTY>1</MINQTY>
<NOTIFY>N</NOTIFY>
<WANTEDSHOW>N</WANTEDSHOW>
<CONDITION></CONDITION>
<WANTEDLISTID>REPLACEME</WANTEDLISTID>
</ITEM>
<ITEM>
<ITEMTYPE>P</ITEMTYPE>
<ITEMID>4032</ITEMID>
<COLOR>6</COLOR>
<MINQTY>2</MINQTY>
<NOTIFY>N</NOTIFY>
<WANTEDSHOW>N</WANTEDSHOW>
<CONDITION></CONDITION>
<WANTEDLISTID>REPLACEME</WANTEDLISTID>
</ITEM>
<ITEM>
<ITEMTYPE>P</ITEMTYPE>
<ITEMID>4032</ITEMID>
<COLOR>1</COLOR>
<MINQTY>4</MINQTY>
<NOTIFY>N</NOTIFY>
<WANTEDSHOW>N</WANTEDSHOW>
<CONDITION></CONDITION>
<WANTEDLISTID>REPLACEME</WANTEDLISTID>
</ITEM>
<ITEM>
<ITEMTYPE>P</ITEMTYPE>
<ITEMID>62462</ITEMID>
<COLOR>1</COLOR>
<MINQTY>4</MINQTY>
<NOTIFY>N</NOTIFY>
<WANTEDSHOW>N</WANTEDSHOW>
<CONDITION></CONDITION>
<WANTEDLISTID>REPLACEME</WANTEDLISTID>
</ITEM>
<ITEM>
<ITEMTYPE>P</ITEMTYPE>
<ITEMID>62462</ITEMID>
<COLOR>5</COLOR>
<MINQTY>2</MINQTY>
<NOTIFY>N</NOTIFY>
<WANTEDSHOW>N</WANTEDSHOW>
<CONDITION></CONDITION>
<WANTEDLISTID>REPLACEME</WANTEDLISTID>
</ITEM>
<ITEM>
<ITEMTYPE>P</ITEMTYPE>
<ITEMID>3679</ITEMID>
<COLOR>86</COLOR>
<MINQTY>5</MINQTY>
<NOTIFY>N</NOTIFY>
<WANTEDSHOW>N</WANTEDSHOW>
<CONDITION></CONDITION>
<WANTEDLISTID>REPLACEME</WANTEDLISTID>
</ITEM>
<ITEM>
<ITEMTYPE>P</ITEMTYPE>
<ITEMID>x77ac50</ITEMID>
<COLOR>11</COLOR>
<MINQTY>1</MINQTY>
<NOTIFY>N</NOTIFY>
<WANTEDSHOW>N</WANTEDSHOW>
<CONDITION></CONDITION>
<WANTEDLISTID>REPLACEME</WANTEDLISTID>
</ITEM>
<ITEM>
<ITEMTYPE>P</ITEMTYPE>
<ITEMID>30395</ITEMID>
<COLOR>85</COLOR>
<MINQTY>1</MINQTY>
<NOTIFY>N</NOTIFY>
<WANTEDSHOW>N</WANTEDSHOW>
<CONDITION></CONDITION>
<WANTEDLISTID>REPLACEME</WANTEDLISTID>
</ITEM>
</INVENTORY>
